linux_nethelp/__init__.py
linux_nethelp/scan_interfaces.py
linux_nethelp-1.0.1.dist-info/DESCRIPTION.rst
linux_nethelp-1.0.1.dist-info/METADATA
linux_nethelp-1.0.1.dist-info/RECORD
linux_nethelp-1.0.1.dist-info/WHEEL
linux_nethelp-1.0.1.dist-info/entry_points.txt
linux_nethelp-1.0.1.dist-info/metadata.json
linux_nethelp-1.0.1.dist-info/top_level.txt
