Metadata-Version: 2.0
Name: linux-nethelp
Version: 1.0.1
Summary: linux network helpers - e.g. list interfaces and their IP addresses
Home-page: https://github.com/haarcuba/linux-nethelp
Author: Yoav Kleinberger
Author-email: haarcuba@gmail.com
License: UNKNOWN
Keywords: linux,interfaces
Platform: UNKNOWN
Classifier: Programming Language :: Python
